cmd2_table/__init__.py
cmd2_table/constants.py
cmd2_table/table_creator.py
cmd2_table/utils.py
cmd2_table-1.0.1.dist-info/licenses/LICENSE
cmd2_table-1.0.1.dist-info/METADATA
cmd2_table-1.0.1.dist-info/WHEEL
cmd2_table-1.0.1.dist-info/top_level.txt
cmd2_table-1.0.1.dist-info/RECORD
