Metadata-Version: 2.4
Name: cmd2_table
Version: 1.0.1
Summary: Backport of cmd2.table_creator module from cmd2 2.7.0 to ease migration to cmd2 3.x
Author: cmd2 Contributors
License-Expression: MIT
Keywords: table,cmd2,Python
Classifier: Development Status :: 5 - Production/Stable
Classifier: Environment :: Console
Classifier: Operating System :: OS Independent
Classifier: Intended Audience :: Developers
Classifier: Intended Audience :: System Administrators
Classifier: Programming Language :: Python :: 3 :: Only
Classifier: Programming Language :: Python :: 3.10
Classifier: Programming Language :: Python :: 3.11
Classifier: Programming Language :: Python :: 3.12
Classifier: Programming Language :: Python :: 3.13
Classifier: Programming Language :: Python :: 3.14
Classifier: Programming Language :: Python :: Free Threading :: 3 - Stable
Classifier: Topic :: Software Development :: Libraries :: Python Modules
Requires-Python: >=3.10
License-File: LICENSE
Requires-Dist: cmd2-ansi>=1.0.1
Requires-Dist: wcwidth>=0.2.13
Dynamic: license-file
